vr/__init__.py
vr/server/__init__.py
vr/server/admin.py
vr/server/bootstrap.py
vr/server/commands.py
vr/server/context_processors.py
vr/server/events.py
vr/server/feeds.py
vr/server/fields.py
vr/server/forms.py
vr/server/gunicorn_config.py
vr/server/manage.py
vr/server/models.py
vr/server/remote.py
vr/server/settings.py
vr/server/storages.py
vr/server/tasks.py
vr/server/urls.py
vr/server/utils.py
vr/server/views.py
vr/server/wsgi.py
vr/server/api/__init__.py
vr/server/api/resources.py
vr/server/api/urls.py
vr/server/api/views.py
vr/server/api/samples/do_build.py
vr/server/balancer/__init__.py
vr/server/balancer/base.py
vr/server/balancer/dummy.py
vr/server/balancer/nginx.py
vr/server/balancer/varnish.py
vr/server/balancer/zxtm.py
vr/server/balancer/zxtm_pool.wsdl
vr/server/migrations/0001_initial.py
vr/server/migrations/0002_auto_20151127_1936.py
vr/server/migrations/__init__.py
vr/server/static/bootstrap/css/bootstrap-3.2.0.min.css
vr/server/static/bootstrap/css/bootstrap.css
vr/server/static/bootstrap/css/bootstrap.min.css
vr/server/static/bootstrap/fonts/glyphicons-halflings-regular.eot
vr/server/static/bootstrap/fonts/glyphicons-halflings-regular.svg
vr/server/static/bootstrap/fonts/glyphicons-halflings-regular.ttf
vr/server/static/bootstrap/fonts/glyphicons-halflings-regular.woff
vr/server/static/bootstrap/img/glyphicons-halflings-white.png
vr/server/static/bootstrap/img/glyphicons-halflings.png
vr/server/static/bootstrap/js/bootstrap-3.2.0.min.js
vr/server/static/bootstrap/js/bootstrap.js
vr/server/static/bootstrap/js/bootstrap.min.js
vr/server/static/css/font-awesome-ie7.css
vr/server/static/css/font-awesome.css
vr/server/static/css/jquery-ui.min.css
vr/server/static/css/multiselect.css
vr/server/static/css/vr.css
vr/server/static/font/FontAwesome.otf
vr/server/static/font/fontawesome-webfont.eot
vr/server/static/font/fontawesome-webfont.svg
vr/server/static/font/fontawesome-webfont.ttf
vr/server/static/font/fontawesome-webfont.woff
vr.server-8.3.dist-info/LICENSE
vr.server-8.3.dist-info/METADATA
vr.server-8.3.dist-info/WHEEL
vr.server-8.3.dist-info/entry_points.txt
vr.server-8.3.dist-info/top_level.txt
vr.server-8.3.dist-info/RECORD
