Metadata-Version: 2.1
Name: vr.server
Version: 8.3
Summary: Velociraptor's Django and Celery components.
Home-page: https://github.com/yougov/vr.server
Author: Brent Tubbs
Author-email: btubbs@gmail.com
License: UNKNOWN
Platform: UNKNOWN
Classifier: Development Status :: 5 - Production/Stable
Classifier: Intended Audience :: Developers
Classifier: License :: OSI Approved :: MIT License
Classifier: Programming Language :: Python :: 2.7
Classifier: Programming Language :: Python :: 3
Requires-Python: >=2.7
Requires-Dist: celery-schedulers (>=0.0.4)
Requires-Dist: diff-match-patch (==20121119)
Requires-Dist: Django (<1.9,>=1.8)
Requires-Dist: django-celery (<3.2,>=3.1.17)
Requires-Dist: django-extensions (==1.5.9)
Requires-Dist: django-picklefield (==0.2.0)
Requires-Dist: django-redis-cache (<2,>=1.7.1)
Requires-Dist: django-reversion (==1.9.3)
Requires-Dist: django-tastypie (==0.12.2)
Requires-Dist: Fabric3
Requires-Dist: gevent (<2,>=1.1rc1)
Requires-Dist: psycogreen
Requires-Dist: gunicorn (>=19.5)
Requires-Dist: psycopg2-binary (>=2.7.5)
Requires-Dist: pymongo (<4,>=2.5.2)
Requires-Dist: redis (<3,>=2.6.2)
Requires-Dist: requests (>=2.11.1)
Requires-Dist: setproctitle
Requires-Dist: sseclient (==0.0.11)
Requires-Dist: six (>=1.4)
Requires-Dist: vr.events (>=2)
Requires-Dist: vr.common (>=6)
Requires-Dist: vr.builder (>=2)
Requires-Dist: vr.imager (>=2)
Requires-Dist: django-yamlfield
Requires-Dist: backports.functools-lru-cache
Requires-Dist: celery (<4dev)
Requires-Dist: jaraco.functools
Requires-Dist: backports.datetime-timestamp
Requires-Dist: tempora
Requires-Dist: jaraco.context
Requires-Dist: path.py (>=10)
Provides-Extra: docs
Requires-Dist: sphinx ; extra == 'docs'
Requires-Dist: jaraco.packaging (>=3.2) ; extra == 'docs'
Requires-Dist: rst.linker (>=1.9) ; extra == 'docs'
Provides-Extra: testing
Requires-Dist: pytest (!=3.7.3,>=3.5) ; extra == 'testing'
Requires-Dist: pytest-checkdocs ; extra == 'testing'
Requires-Dist: pytest-flake8 ; extra == 'testing'
Requires-Dist: backports.unittest-mock ; extra == 'testing'
Requires-Dist: jaraco.mongodb (>=3.11) ; extra == 'testing'
Requires-Dist: python-dateutil (>=2.4) ; extra == 'testing'
Requires-Dist: jaraco.postgres (>=1.3.1) ; extra == 'testing'
Requires-Dist: pytest-services ; extra == 'testing'
